D_FlipFlop/design.v
module dff (rst, clk, d, q);
input rst, clk, d;
output reg  q;

always @(posedge clk)begin
if(rst == 1'b1) begin
q <= 1'b0;
end
else begin
q <= d;
end
end
endmodule

DFlipFlop/testbench.v
module tb;

reg clk, rst, d;
wire q;

dff uut (
    .rst(rst),
    .clk(clk),
    .d(d),
    .q(q)
);


always begin   //always #50 clk = ~clk; alter method
clk <= 1'b0; #50;
clk <= 1'b1;#50; 
end

initial begin
rst <= 1'b1; #100;
rst <= 1'b0; #100;
d <= 1'b1; #100;
d <= 1'b0; #100;
$finish;
end

initial begin
$dumpfile("dump.vcd");
$dumpvars(0);
end
endmodule

D_FlipFlop/dump.vcd
$date
	Mon Jun 22 20:26:38 2026
$end
$version
	Icarus Verilog
$end
$timescale
	1s
$end
$scope module tb $end
$var wire 1 ! q $end
$var reg 1 " clk $end
$var reg 1 # d $end
$var reg 1 $ rst $end
$scope module uut $end
$var wire 1 " clk $end
$var wire 1 # d $end
$var wire 1 $ rst $end
$var reg 1 ! q $end
$upscope $end
$upscope $end
$enddefinitions $end
$comment Show the parameter values. $end
$dumpall
$end
#0
$dumpvars
1$
x#
0"
x!
$end
#50
0!
1"
#100
0"
0$
#150
x!
1"
#200
0"
1#
#250
1!
1"
#300
0"
0#
#350
0!
1"
