Multiplexer/2x1mux/design.v
module mux(a, b ,s ,y);

input s;
input [1:0] a, b;
output [1:0] y;

assign y = (s == 1'b0) ? a : b; // Using Continuous Assignment

endmodule

Multiplexer/2x1mux/testbench.v
module tb ();

reg s;
reg [1:0]a, b;
wire [1:0]y;

mux dut (
.a(a),
.b(b),
.s(s),
.y(y)
);

initial begin
    a=2'b00; b=2'b00; s=0; #10; s=1; #10;
    a=2'b00; b=2'b01; s=0; #10; s=1; #10;
    a=2'b00; b=2'b10; s=0; #10; s=1; #10;
    a=2'b00; b=2'b11; s=0; #10; s=1; #10;
    a=2'b01; b=2'b00; s=0; #10; s=1; #10;
    a=2'b01; b=2'b01; s=0; #10; s=1; #10;
    a=2'b01; b=2'b10; s=0; #10; s=1; #10;
    a=2'b01; b=2'b11; s=0; #10; s=1; #10;
    a=2'b10; b=2'b00; s=0; #10; s=1; #10;
    a=2'b10; b=2'b01; s=0; #10; s=1; #10;
    a=2'b10; b=2'b10; s=0; #10; s=1; #10;
    a=2'b10; b=2'b11; s=0; #10; s=1; #10;
    a=2'b11; b=2'b00; s=0; #10; s=1; #10;
    a=2'b11; b=2'b01; s=0; #10; s=1; #10;
    a=2'b11; b=2'b10; s=0; #10; s=1; #10;
    a=2'b11; b=2'b11; s=0; #10; s=1; #10;
    $finish;
end

initial begin 
$dumpfile("dump.vcd");
$dumpvars(0);
end
endmodule

Multiplexer/2x1mux/dump.vcd
$date
	Mon Jun 15 20:13:11 2026
$end
$version
	Icarus Verilog
$end
$timescale
	1s
$end
$scope module tb $end
$var wire 2 ! y [1:0] $end
$var reg 2 " a [1:0] $end
$var reg 2 # b [1:0] $end
$var reg 1 $ s $end
$scope module dut $end
$var wire 2 % a [1:0] $end
$var wire 2 & b [1:0] $end
$var wire 1 $ s $end
$var wire 2 ' y [1:0] $end
$upscope $end
$upscope $end
$enddefinitions $end
$comment Show the parameter values. $end
$dumpall
$end
#0
$dumpvars
b0 '
b0 &
b0 %
0$
b0 #
b0 "
b0 !
$end
#10
1$
#20
b0 !
b0 '
0$
b1 #
b1 &
#30
b1 !
b1 '
1$
#40
b0 !
b0 '
0$
b10 #
b10 &
#50
b10 !
b10 '
1$
#60
b0 !
b0 '
0$
b11 #
b11 &
#70
b11 !
b11 '
1$
#80
b1 !
b1 '
0$
b0 #
b0 &
b1 "
b1 %
#90
b0 !
b0 '
1$
#100
b1 !
b1 '
0$
b1 #
b1 &
#110
1$
#120
b1 !
b1 '
0$
b10 #
b10 &
#130
b10 !
b10 '
1$
#140
b1 !
b1 '
0$
b11 #
b11 &
#150
b11 !
b11 '
1$
#160
b10 !
b10 '
0$
b0 #
b0 &
b10 "
b10 %
#170
b0 !
b0 '
1$
#180
b10 !
b10 '
0$
b1 #
b1 &
#190
b1 !
b1 '
1$
#200
b10 !
b10 '
0$
b10 #
b10 &
#210
1$
#220
b10 !
b10 '
0$
b11 #
b11 &
#230
b11 !
b11 '
1$
#240
b11 !
b11 '
0$
b0 #
b0 &
b11 "
b11 %
#250
b0 !
b0 '
1$
#260
b11 !
b11 '
0$
b1 #
b1 &
#270
b1 !
b1 '
1$
#280
b11 !
b11 '
0$
b10 #
b10 &
#290
b10 !
b10 '
1$
#300
b11 !
b11 '
0$
b11 #
b11 &
#310
1$
