combinational_circuit/comb_circuit1/design.v
module comb_circuit1 (a, b, c, y);

input a, b, c;
output y;
wire a_and_b, a_or_b;

assign a_and_b = (~(a & b));
assign a_or_b = (~(a | b));
assign y = (a_and_b) & (a_or_b) & (c);


endmodule

combinational_circuit/comb_circuit1/testbench.v
module tb () ;
reg a, b, c;
wire y;

comb_circuit1 dut (
    .a(a),
    .b(b),
    .c(c),
    .y(y)
);

initial begin
a = 1'b0; b = 1'b0; c = 1'b0; #100;
a = 1'b0; b = 1'b0; c = 1'b1; #100;
a = 1'b0; b = 1'b1; c = 1'b0; #100;
a = 1'b0; b = 1'b1; c = 1'b1; #100;
a = 1'b1; b = 1'b0; c = 1'b0; #100;
a = 1'b1; b = 1'b0; c = 1'b1; #100;
a = 1'b1; b = 1'b1; c = 1'b0; #100;
a = 1'b1; b = 1'b1; c = 1'b1; #100;
end

initial begin
$dumpfile("dump.vcd");
$dumpvars(0);
end

endmodule

combinational_circuit/comb_circuit1/dump.vcd
$date
	Sun Jun 14 22:39:28 2026
$end
$version
	Icarus Verilog
$end
$timescale
	1s
$end
$scope module tb $end
$var wire 1 ! y $end
$var reg 1 " a $end
$var reg 1 # b $end
$var reg 1 $ c $end
$scope module dut $end
$var wire 1 " a $end
$var wire 1 % a_and_b $end
$var wire 1 & a_or_b $end
$var wire 1 # b $end
$var wire 1 $ c $end
$var wire 1 ! y $end
$upscope $end
$upscope $end
$enddefinitions $end
$comment Show the parameter values. $end
$dumpall
$end
#0
$dumpvars
1&
1%
0$
0#
0"
0!
$end
#100
1!
1$
#200
0&
0!
0$
1#
#300
1$
#400
0$
0#
1"
#500
1$
#600
0%
0$
1#
#700
1$
