sequecational_circuit/sequ_circuit1/design.v
module seq(a, b, c, clk, rst, y);
input a, b, c, clk, rst;
output y;

wire com_1, com_2;
reg reg_1, reg_2;

assign com_1 = (a | b) & c;
assign com_2 = ~reg_1;
assign y = ~reg_2; 

always @(posedge clk or posedge rst)
begin

if(rst == 1'b1)
begin
reg_1 <= 1'b1;
reg_2 <= 1'b1;
end 

else

begin
reg_1 <= com_1;
reg_2 <= com_2;
end

end
endmodule

sequecational_circuit/sequ_circuit1/testbench.v
module tb;
reg a, b, c;
reg clk, rst;
wire y;

seq uut (
    .a(a),
    .b(b),
    .c(c),
    .clk(clk),
    .rst(rst),
    .y(y)
);

initial begin
    $dumpfile("dump.vcd");
    $dumpvars(0,tb);
end

initial begin
    clk = 1'b0;
    forever #50 clk = ~clk;
end

initial begin
    rst = 1'b1;
    a = 1'b0; b = 1'b0; c = 1'b0; #100;

    rst = 1'b0;
    a = 1'b0; b = 1'b0; c = 1'b0; #100;
    a = 1'b0; b = 1'b0; c = 1'b1; #100;
    a = 1'b0; b = 1'b1; c = 1'b0; #100;
    a = 1'b0; b = 1'b1; c = 1'b1; #100;
    a = 1'b1; b = 1'b0; c = 1'b0; #100;
    a = 1'b1; b = 1'b0; c = 1'b1; #100;
    a = 1'b1; b = 1'b1; c = 1'b0; #100;
    a = 1'b1; b = 1'b1; c = 1'b1; #100;
    $finish;
end

endmodule

sequecational_circuit/sequ_circuit1/dump.vcd
$date
	Wed Jul 08 21:00:45 2026
$end
$version
	Icarus Verilog
$end
$timescale
	1s
$end
$scope module tb $end
$var wire 1 ! y $end
$var reg 1 " a $end
$var reg 1 # b $end
$var reg 1 $ c $end
$var reg 1 % clk $end
$var reg 1 & rst $end
$scope module uut $end
$var wire 1 " a $end
$var wire 1 # b $end
$var wire 1 $ c $end
$var wire 1 % clk $end
$var wire 1 ' com_1 $end
$var wire 1 ( com_2 $end
$var wire 1 & rst $end
$var wire 1 ! y $end
$var reg 1 ) reg_1 $end
$var reg 1 * reg_2 $end
$upscope $end
$upscope $end
$enddefinitions $end
$comment Show the parameter values. $end
$dumpall
$end
#0
$dumpvars
1*
1)
0(
0'
1&
0%
0$
0#
0"
0!
$end
#50
1%
#100
0%
0&
#150
1!
1(
0*
0)
1%
#200
0%
1$
#250
0!
1*
1%
#300
0%
0$
1#
#350
1%
#400
1'
0%
1$
#450
0(
1)
1%
#500
0'
0%
0$
0#
1"
#550
1!
1(
0*
0)
1%
#600
1'
0%
1$
#650
0!
0(
1*
1)
1%
#700
0'
0%
0$
1#
#750
1!
1(
0*
0)
1%
#800
1'
0%
1$
#850
0!
0(
1*
1)
1%
